llama_index/readers/apify/__init__.py
llama_index/readers/apify/actor/__init__.py
llama_index/readers/apify/actor/base.py
llama_index/readers/apify/dataset/__init__.py
llama_index/readers/apify/dataset/base.py
llama_index_readers_apify-0.4.1.dist-info/METADATA
llama_index_readers_apify-0.4.1.dist-info/WHEEL
llama_index_readers_apify-0.4.1.dist-info/licenses/LICENSE
llama_index_readers_apify-0.4.1.dist-info/RECORD
