Metadata-Version: 2.4
Name: llama-index-readers-apify
Version: 0.4.1
Summary: llama-index readers apify integration
Author-email: Your Name <you@example.com>
Maintainer: drobnikj
License-Expression: MIT
License-File: LICENSE
Keywords: apify,crawler,scraper,scraping
Requires-Python: <4.0,>=3.9
Requires-Dist: apify-client<2,>=1.6.2
Requires-Dist: llama-index-core<0.15,>=0.13.0
